legions/__init__.py
legions/context.py
legions/main.py
legions/plugin.py
legions/statusbar.py
legions/version.py
legions/commands/commands.py
legions/commands/more/__init__.py
legions/commands/more/ens.py
legions/commands/more/more_commands.py
legions/network/web3.py
legions/utils/chains.json
legions/utils/helper_functions.py
legions-0.8.4.dist-info/METADATA
legions-0.8.4.dist-info/WHEEL
legions-0.8.4.dist-info/entry_points.txt
legions-0.8.4.dist-info/top_level.txt
legions-0.8.4.dist-info/RECORD
