Metadata-Version: 2.1
Name: legions
Version: 0.8.4
Summary: UNKNOWN
Home-page: https://github.com/consensys/Legions
Author: Shayan Eskandari - ConsenSys Diligence
Author-email: shayan.eskandari@consensys.net
License: MIT
Platform: UNKNOWN
Requires-Dist: web3 (==5.7.0)
Requires-Dist: python-nubia (==0.2b2)
Requires-Dist: requests
Requires-Dist: tabulate
Requires-Dist: dataclasses ; python_version >= "3.6"
